redisgetapi/__init__.py
redisgetapi/fetch.py
redisgetapi/testfetch.py
redisgetapi-0.0.1.dist-info/LICENSE
redisgetapi-0.0.1.dist-info/METADATA
redisgetapi-0.0.1.dist-info/WHEEL
redisgetapi-0.0.1.dist-info/top_level.txt
redisgetapi-0.0.1.dist-info/RECORD
