Metadata-Version: 2.1
Name: redisgetapi
Version: 0.0.1
Summary: This package is used to handl redis persistence
Home-page: https://nkrtech.com
Download-URL: https://github.com/moinonin/redisgetapi/archive/refs/heads/main.zip
Author: Nicolus Rotich
Author-email: nicholas.rotich@gmail.com
License: MIT
Project-URL: Bug Tracker, https://github.com/pypa/redisgetapi/issues
Platform: any
Classifier: License :: OSI Approved :: MIT License
Requires-Python: >=3.9
License-File: LICENSE
Requires-Dist: setuptools (>=58.1.0)
Requires-Dist: wheel (>=0.36.2)
Requires-Dist: redis (==4.1.2)
Requires-Dist: requests (==2.27.1)
Requires-Dist: fire
